observation/__init__.py
observation/esconstante.py
observation/esobservation.py
observation/essearch.py
observation/esvalue.py
observation/esvalue_base.py
observation/iindex.py
observation/iindex_interface.py
observation/iindex_structure.py
observation/ilist.py
observation/ilist_analysis.py
observation/ilist_interface.py
observation/ilist_structure.py
observation/timeslot.py
observation/util.py
observation-0.0.5.dist-info/LICENSE.txt
observation-0.0.5.dist-info/METADATA
observation-0.0.5.dist-info/WHEEL
observation-0.0.5.dist-info/top_level.txt
observation-0.0.5.dist-info/RECORD
