Metadata-Version: 2.1
Name: observation
Version: 0.0.5
Summary: environmental data interoperability
Home-page: https://github.com/loco-philippe/Environmental-Sensing
Author: Philippe Thomy
Author-email: philippe@loco-labs.io
Keywords: observation,tabular data,development,environmental data
Classifier: Development Status :: 3 - Alpha
Classifier: Intended Audience :: Developers
Classifier: Topic :: Software Development :: Build Tools
Classifier: License :: OSI Approved :: MIT License
Classifier: Programming Language :: Python :: 3
Requires-Python: >=3.7, <4
License-File: LICENSE.txt
Requires-Dist: numpy
Requires-Dist: shapely
Requires-Dist: cbor2
Requires-Dist: xarray
Requires-Dist: pandas
Requires-Dist: folium
Requires-Dist: bson
